victoria_email/__init__.py
victoria_email/load_test.py
victoria_email/reconstruct_mail.py
victoria_email/recover_mail.py
victoria_email/replay_deadletters.py
victoria_email/schemas.py
victoria_email/send_mail.py
victoria_email/core/__init__.py
victoria_email/core/blob_storage.py
victoria_email/core/config.py
victoria_email/core/mail_reconstruction.py
victoria_email/core/service_bus.py
victoria_email/core/util.py
victoria_email-1.1.2.dist-info/LICENSE
victoria_email-1.1.2.dist-info/METADATA
victoria_email-1.1.2.dist-info/WHEEL
victoria_email-1.1.2.dist-info/top_level.txt
victoria_email-1.1.2.dist-info/RECORD
