Metadata-Version: 2.1
Name: victoria-email
Version: 1.1.2
Summary: Victoria plugin for Glasswall Rebuild for Email
Home-page: https://github.com/glasswall-sre/victoria_email
Author: Sam Gibson
Author-email: sgibson@glasswallsolutions.com
License: UNKNOWN
Platform: UNKNOWN
Requires-Python: >=3.7
Requires-Dist: victoria
Requires-Dist: aiohttp (>=3.5.4)
Requires-Dist: aiorun
Requires-Dist: cchardet
Requires-Dist: aiodns
Requires-Dist: azure-servicebus (<=0.50.1)
Requires-Dist: azure-storage-blob (>=2.1.0)
Requires-Dist: sremail
Requires-Dist: roundrobin
Requires-Dist: boto3
